<speech>
   <id>8be77567-43b0-49a5-b82e-152fe5ca4a78</id>
   <speaker>
      <id>65f60a71-5b92-46ea-ac2d-89e7fa811cf8</id>
      <name>Christina Weiss</name>
      <party></party>
   </speaker>
   <text>
   Sehr geehrte Frau Landsberger,liebe Freunde des europäischen Kinos,
   ich freue mich sehr, heute abend hier zu sein. Wenn ich in den Saal schaue, sehe ich das junge Gesicht des alten Europa. Es ist nicht nur jung, es hat Ausdruck. Es kennt noch die Spuren des Lampenfiebers. Es weiß aber auch um die Vergänglichkeit des Ruhms, der sich nur mit Talent  entwickeln und bewahren lässt. Sie alle hier besitzen Talent, viel Talent sogar, sonst wären Sie nicht hier. Und für diese Gabe kenne ich einen schönen Pflegehinweis. Er stammt von einem der größten Stars des 20. Jahrhunderts, von Frank Sinatra: "Man darf sein  Talent nicht vergeuden. Jene, die Talent haben, sollten es festhalten, in die Arme schließen, es nähren und andere daran teilhaben lassen. Ansonsten könnte man es dir so schnell nehmen, wie man es dir gegeben hat." Ich wünsche Ihnen allen das Talent, ihr Talent zu bewahren, und dem europäischen Kino noch viele Entdeckungen wie Sie es sind. Herzlich willkommen in Berlin!
   </text>
   <url>Bundesregierung.xml</url>
</speech>